[
  {
    "definition": "to cause to be estranged : to make unfriendly, hostile, or indifferent especially where attachment formerly existed",
    "examples": [
      "He alienated most of his colleagues with his bad temper.",
      "Her position on this issue has alienated many former supporters."
    ]
  },
  {
    "definition": "to convey or transfer (something, such as property or a right) usually by a specific act rather than the due course of law",
    "examples": []
  },
  {
    "definition": "to cause to be withdrawn or diverted",
    "examples": [
      "alienate capital from its natural channels"
    ]
  }
]