[
  {
    "definition": "to put right, to make emendations in (something, such as a text)",
    "examples": [
      "amended the manuscript"
    ]
  },
  {
    "definition": "to change or modify (something) for the better : improve",
    "examples": [
      "amend the situation"
    ]
  },
  {
    "definition": "to alter especially in phraseology, to alter formally by modification, deletion, or addition",
    "examples": [
      "amend a constitution"
    ]
  },
  {
    "definition": "to reform oneself",
    "examples": []
  }
]