[
  {
    "definition": "the process of altering or amending a law or document (such as a constitution) by parliamentary or constitutional procedure",
    "examples": [
      "rights that were granted by amendment of the Constitution"
    ]
  },
  {
    "definition": "an alteration proposed or effected by this process",
    "examples": [
      "a constitutional amendment"
    ]
  },
  {
    "definition": "the act of amending something : correction",
    "examples": []
  },
  {
    "definition": "a material (such as compost or sand) that aids plant growth indirectly by improving the condition of the soil",
    "examples": [
      "soil amendments"
    ]
  }
]