[
  {
    "definition": "to set or stud with or as if with ornaments",
    "examples": [
      "a crown beset with rubies",
      "… leaves, whose edges were beset with thorns …",
      "— J. G. Frazer"
    ]
  },
  {
    "definition": "trouble, harass",
    "examples": [
      "inflation besets the economy"
    ]
  },
  {
    "definition": "to set upon : assail",
    "examples": [
      "the explorers were beset by wolves"
    ]
  },
  {
    "definition": "to hem in : surround",
    "examples": [
      "a town beset with high mountains"
    ]
  }
]