[
  {
    "definition": "a judgment involving condemnation",
    "examples": [
      "unorthodox practices awaiting the censure of the city council"
    ]
  },
  {
    "definition": "the act of blaming or condemning sternly",
    "examples": [
      "The country faces international censure for its alleged involvement in the assassination."
    ]
  },
  {
    "definition": "an official reprimand",
    "examples": [
      "The lawyer\u0027s misconduct resulted in a letter of censure from the judge."
    ]
  },
  {
    "definition": "opinion, judgment",
    "examples": []
  },
  {
    "definition": "to find fault with and criticize as blameworthy",
    "examples": [
      "She would tell him it was … no sign of a good pastor to be eternally censuring his flock.",
      "— Charlotte Brontë"
    ]
  },
  {
    "definition": "to formally reprimand (someone) : to express official censure of (someone)",
    "examples": [
      "While a vote to censure the president has no legal ramifications, it is a significant and rare symbolic vote of disapproval.",
      "— Emma Loop"
    ]
  },
  {
    "definition": "estimate, judge",
    "examples": []
  }
]