[
  {
    "definition": "noisy shouting",
    "examples": [
      "a clamor of children at play"
    ]
  },
  {
    "definition": "a loud continuous noise",
    "examples": [
      "the clamor of the waterfall"
    ]
  },
  {
    "definition": "insistent public expression (as of support or protest)",
    "examples": [
      "the current clamor about what is wrong with our schools"
    ]
  },
  {
    "definition": "to make a din (see din entry 1 sense 1)",
    "examples": [
      "The children clamored around them, singing songs and laughing."
    ]
  },
  {
    "definition": "to become loudly insistent",
    "examples": [
      "clamored for his impeachment",
      "clamoring for full independence"
    ]
  },
  {
    "definition": "to utter or proclaim insistently and noisily",
    "examples": [
      "cart peddlers clamored their wares",
      "— Walter Farley"
    ]
  },
  {
    "definition": "to influence by means of clamor",
    "examples": []
  },
  {
    "definition": "silence",
    "examples": []
  }
]