[
  {
    "definition": "skill in planning, making, or executing : dexterity",
    "examples": [
      "\"We have not the strength with which to fight this man; we must … win, if win we can, by craft.\"",
      "— Jack London"
    ]
  },
  {
    "definition": "an occupation or trade requiring manual dexterity or artistic skill",
    "examples": [
      "the carpenter\u0027s craft",
      "the craft of writing plays",
      "crafts such as pottery, carpentry, and sewing",
      "He learned the craft as an apprentice."
    ]
  },
  {
    "definition": "articles made by craftspeople",
    "examples": [
      "a store selling crafts",
      "a crafts fair"
    ]
  },
  {
    "definition": "skill in deceiving to gain an end",
    "examples": [
      "used craft and guile to close the deal"
    ]
  },
  {
    "definition": "the members of a trade or trade association",
    "examples": []
  },
  {
    "definition": "a boat especially of small size",
    "examples": []
  },
  {
    "definition": "aircraft",
    "examples": []
  },
  {
    "definition": "spacecraft",
    "examples": []
  },
  {
    "definition": "to make or produce with care, skill, or ingenuity",
    "examples": [
      "She is crafting a new sculpture.",
      "a carefully crafted story"
    ]
  }
]