[
  {
    "definition": "marked by the primitive, gross, or elemental or by uncultivated simplicity or vulgarity",
    "examples": [
      "a crude stereotype",
      "crude tools",
      "crude jokes"
    ]
  },
  {
    "definition": "existing in a natural state and unaltered by cooking or processing",
    "examples": [
      "crude oil",
      "crude ore"
    ]
  },
  {
    "definition": "rough or inexpert in plan or execution",
    "examples": [
      "a crude shelter"
    ]
  },
  {
    "definition": "lacking a covering, glossing, or concealing element : obvious",
    "examples": [
      "crude facts"
    ]
  },
  {
    "definition": "tabulated without being broken down into classes",
    "examples": [
      "the crude death rate"
    ]
  },
  {
    "definition": "unripe, immature",
    "examples": []
  },
  {
    "definition": "a substance in its natural unprocessed state, unrefined petroleum",
    "examples": []
  }
]