[
  {
    "definition": "having or showing the attitude or temper of a cynic: such as",
    "examples": []
  },
  {
    "definition": "contemptuously distrustful of human nature and motives",
    "examples": [
      "… those cynical men who say that democracy cannot be honest and efficient.",
      "— Franklin D. Roosevelt"
    ]
  },
  {
    "definition": "based on or reflecting a belief that human conduct is motivated primarily by self-interest",
    "examples": [
      "a cynical ploy to win votes"
    ]
  },
  {
    "definition": "captious, peevish",
    "examples": []
  }
]