[
  {
    "definition": "a noxious gas — compare black damp, firedamp",
    "examples": []
  },
  {
    "definition": "moisture:",
    "examples": []
  },
  {
    "definition": "humidity, dampness",
    "examples": []
  },
  {
    "definition": "fog, mist",
    "examples": []
  },
  {
    "definition": "discouragement, check",
    "examples": []
  },
  {
    "definition": "depression, dejection",
    "examples": []
  },
  {
    "definition": "to affect with or as if with a noxious gas : choke",
    "examples": []
  },
  {
    "definition": "to diminish the activity or intensity of",
    "examples": [
      "damping down the causes of inflation",
      "liquid damps out compass oscillations"
    ]
  },
  {
    "definition": "to check the vibration or oscillation of (something, such as a string or a voltage)",
    "examples": []
  },
  {
    "definition": "dampen",
    "examples": []
  },
  {
    "definition": "to diminish progressively in vibration or oscillation",
    "examples": []
  },
  {
    "definition": "being confused, bewildered, or shocked : stupefied",
    "examples": []
  },
  {
    "definition": "depressed, dull",
    "examples": []
  },
  {
    "definition": "slightly or moderately wet : moist, humid",
    "examples": [
      "a damp towel",
      "damp weather"
    ]
  }
]