[
  {
    "definition": "of, relating to, or proceeding directly from God (see god entry 1 sense 1) or a god (see god entry 1 sense 2)",
    "examples": [
      "divine inspiration",
      "divine love",
      "praying for divine intervention"
    ]
  },
  {
    "definition": "being a deity",
    "examples": [
      "the divine Savior",
      "a divine ruler"
    ]
  },
  {
    "definition": "directed to a deity",
    "examples": [
      "divine worship"
    ]
  },
  {
    "definition": "supremely good : superb",
    "examples": [
      "The meal was just divine."
    ]
  },
  {
    "definition": "heavenly, godlike",
    "examples": []
  },
  {
    "definition": "clergyman",
    "examples": [
      "a Puritan divine"
    ]
  },
  {
    "definition": "theologian",
    "examples": []
  },
  {
    "definition": "to discover by intuition or insight : infer",
    "examples": [
      "divine the truth"
    ]
  },
  {
    "definition": "to discover or locate (something, such as underground water or minerals) usually by means of a divining rod",
    "examples": []
  },
  {
    "definition": "to seek to predict future events or discover hidden knowledge usually by the interpretation of omens or by the aid of supernatural powers : to practice divination : prophesy",
    "examples": []
  },
  {
    "definition": "to perceive intuitively",
    "examples": []
  }
]