[
  {
    "definition": "a poem in elegiac couplets",
    "examples": []
  },
  {
    "definition": "a song or poem expressing sorrow or lamentation especially for one who is dead",
    "examples": []
  },
  {
    "definition": "something (such as a speech) resembling such a song or poem",
    "examples": []
  },
  {
    "definition": "a pensive or reflective poem that is usually nostalgic or melancholy",
    "examples": []
  },
  {
    "definition": "a short pensive musical composition",
    "examples": []
  }
]