[
  {
    "definition": "companionship, company",
    "examples": [
      "looking for the fellowship of friendly people"
    ]
  },
  {
    "definition": "community of interest, activity, feeling, or experience",
    "examples": [
      "their fellowship in crime",
      "— A. J. Ayer"
    ]
  },
  {
    "definition": "the state of being a fellow or associate",
    "examples": []
  },
  {
    "definition": "a company of equals or friends : association",
    "examples": [
      "a youth fellowship"
    ]
  },
  {
    "definition": "the quality or state of being comradely",
    "examples": [
      "meaningful communication for building trust and fellowship"
    ]
  },
  {
    "definition": "membership, partnership",
    "examples": []
  },
  {
    "definition": "the position of a fellow (as of a university)",
    "examples": [
      "applied for a research fellowship in physics"
    ]
  },
  {
    "definition": "the stipend of a fellow",
    "examples": []
  },
  {
    "definition": "a foundation for the providing of such a stipend",
    "examples": []
  },
  {
    "definition": "to join in fellowship especially with a church member",
    "examples": []
  },
  {
    "definition": "to admit to fellowship (as in a church)",
    "examples": []
  }
]