[
  {
    "definition": "to furnish or fit with glass",
    "examples": []
  },
  {
    "definition": "to coat with or as if with a glaze",
    "examples": [
      "the storm glazed trees with ice"
    ]
  },
  {
    "definition": "to apply a glaze to",
    "examples": [
      "glaze doughnuts"
    ]
  },
  {
    "definition": "to give a smooth glossy surface to",
    "examples": []
  },
  {
    "definition": "to become glazed or glassy",
    "examples": [
      "my eyes glazed over"
    ]
  },
  {
    "definition": "to form a glaze",
    "examples": []
  },
  {
    "definition": "a smooth slippery coating of thin ice",
    "examples": []
  },
  {
    "definition": "a liquid preparation applied to food on which it forms a firm glossy coating, a mixture mostly of oxides (such as silica and alumina) applied to the surface of ceramic wares to form a moisture-impervious and often lustrous or ornamental coating",
    "examples": []
  },
  {
    "definition": "a transparent or translucent color applied to modify the effect of a painted surface",
    "examples": []
  },
  {
    "definition": "a smooth glossy or lustrous surface or finish",
    "examples": []
  },
  {
    "definition": "a glassy film",
    "examples": []
  },
  {
    "definition": "stare",
    "examples": []
  }
]