[
  {
    "definition": "listen",
    "examples": [
      "hearkened without much mental comment",
      "— Theodore Dreiser"
    ]
  },
  {
    "definition": "to give respectful attention",
    "examples": [
      "the humble folk who hearkened to these evangelists",
      "— G. M. Stephenson"
    ]
  },
  {
    "definition": "to bring to mind something in the past : hearken back",
    "examples": [
      "Portrayals of dinosaurs with lizard-like tongues hearken to early interpretations of the beasts as oversized lizards.",
      "— Mindy Weisberger"
    ]
  },
  {
    "definition": "to give heed to : hear",
    "examples": []
  }
]