[
  {
    "definition": "a jointed or flexible device on which a door, lid, or other swinging part turns",
    "examples": []
  },
  {
    "definition": "a flexible ligamentous joint",
    "examples": []
  },
  {
    "definition": "a small piece of thin gummed paper used in fastening a postage stamp in an album",
    "examples": []
  },
  {
    "definition": "a determining factor : turning point",
    "examples": []
  },
  {
    "definition": "to swing on or as if on a hinge",
    "examples": [
      "These thoughtful amenities include … an outdoor patio TV that hinges outward toward the pool …",
      "— Paul Takahashi",
      "… we pulled within feet of a 12-foot crocodile, his huge jaw hinging open in warning to reveal a toothy grin.",
      "— Andrea Bartz"
    ]
  },
  {
    "definition": "to be contingent on a single consideration or point",
    "examples": [
      "the prosecution\u0027s case hinges on the DNA evidence"
    ]
  },
  {
    "definition": "to attach by or furnish with hinges",
    "examples": []
  }
]