[
  {
    "definition": "a domesticated swine especially when weighing more than 120 pounds (54 kilograms) — compare pig sense 1a",
    "examples": []
  },
  {
    "definition": "any of various animals related to the domesticated swine",
    "examples": []
  },
  {
    "definition": "a young unshorn sheep, wool from such a sheep",
    "examples": []
  },
  {
    "definition": "a selfish, gluttonous, or filthy person",
    "examples": []
  },
  {
    "definition": "one that uses something to excess",
    "examples": [
      "old cars that are gas hogs"
    ]
  },
  {
    "definition": "to cut (a horse\u0027s mane) short : roach",
    "examples": []
  },
  {
    "definition": "to cause to arch",
    "examples": []
  },
  {
    "definition": "to take in excess of one\u0027s due",
    "examples": [
      "hog the credit"
    ]
  },
  {
    "definition": "to tear up or shred (some material, such as waste wood) into bits by machine",
    "examples": []
  },
  {
    "definition": "to become curved upward in the middle",
    "examples": []
  }
]