[
  {
    "definition": "something that is inferred, a conclusion or opinion that is formed because of known facts or evidence",
    "examples": []
  },
  {
    "definition": "the act or process of inferring (see infer): such as",
    "examples": []
  },
  {
    "definition": "the act of passing from one proposition, statement, or judgment considered as true to another whose truth is believed to follow from that of the former",
    "examples": []
  },
  {
    "definition": "the act of passing from statistical sample data to generalizations (as of the value of population parameters) usually with calculated degrees of certainty",
    "examples": []
  },
  {
    "definition": "the premises and conclusion of a process of inferring",
    "examples": []
  }
]