[
  {
    "definition": "to pronounce the sibilants \\s\\ and \\z\\ imperfectly especially by turning them into \\th\\ and \\t͟h\\",
    "examples": []
  },
  {
    "definition": "to speak falteringly, childishly, or with a lisp",
    "examples": []
  },
  {
    "definition": "to utter falteringly or with a lisp",
    "examples": []
  },
  {
    "definition": "a speech defect or affectation characterized by lisping",
    "examples": []
  },
  {
    "definition": "a sound resembling a lisp",
    "examples": []
  },
  {
    "definition": "a computer programming language that is designed for easy manipulation of symbols that represent data and instructions and is used extensively for work in artificial intelligence",
    "examples": []
  }
]