[
  {
    "definition": "to grind or mix thoroughly : pulverize",
    "examples": [
      "mull a portion of the pigment with the oil",
      "— H. J. Wolfe"
    ]
  },
  {
    "definition": "to consider at length : ponder",
    "examples": [
      "mulled over his choices",
      "It\u0027s a fine offer, but we need time to mull it over."
    ]
  },
  {
    "definition": "meditate, ponder",
    "examples": [
      "all his talk of mulling and weighing and balancing was vacillation",
      "— J. P. Marquand"
    ]
  },
  {
    "definition": "to heat, sweeten, and flavor (a beverage, such as wine or cider) with spices",
    "examples": []
  },
  {
    "definition": "a soft fine sheer fabric of cotton, silk, or rayon",
    "examples": []
  },
  {
    "definition": "friable forest humus that forms a layer of mixed organic matter and mineral soil and merges gradually into the mineral soil beneath",
    "examples": []
  },
  {
    "definition": "a finely powdered solid especially in a suspension",
    "examples": []
  },
  {
    "definition": "island of western Scotland in the Inner Hebrides area 351 square miles (913 square kilometers), population 1499",
    "examples": []
  }
]