[
  {
    "definition": "an estate inherited from one\u0027s father or ancestor",
    "examples": [
      "there were always children, and the patrimony was divided every time",
      "— D. H. Lawrence"
    ]
  },
  {
    "definition": "anything derived from one\u0027s father or ancestors : heritage",
    "examples": [
      "These historic landmarks are an important part of our cultural patrimony."
    ]
  },
  {
    "definition": "an estate or endowment belonging by ancient right to a church",
    "examples": [
      "canon law … aims at conserving the patrimony of the diocese",
      "— T. J. Reese"
    ]
  }
]