[
  {
    "definition": "to utter by or as if by divine inspiration",
    "examples": []
  },
  {
    "definition": "to predict with assurance or on the basis of mystic knowledge",
    "examples": []
  },
  {
    "definition": "prefigure",
    "examples": []
  },
  {
    "definition": "to speak as if divinely inspired",
    "examples": []
  },
  {
    "definition": "to give instruction in religious matters : preach",
    "examples": []
  },
  {
    "definition": "to make a prediction",
    "examples": []
  }
]