[
  {
    "definition": "an item-by-item report or review : summary",
    "examples": []
  },
  {
    "definition": "a play in baseball in which a base runner who is caught off base is chased by two or more opposing players who throw the ball from one to another in an attempt to tag the runner out",
    "examples": []
  },
  {
    "definition": "being in poor repair : dilapidated",
    "examples": []
  },
  {
    "definition": "worn-out, exhausted",
    "examples": []
  },
  {
    "definition": "completely unwound",
    "examples": []
  },
  {
    "definition": "to collide with and knock down",
    "examples": []
  },
  {
    "definition": "to run against and cause to sink",
    "examples": []
  },
  {
    "definition": "to chase to exhaustion or until captured",
    "examples": []
  },
  {
    "definition": "to trace the source of",
    "examples": []
  },
  {
    "definition": "to tag out (a base runner) between bases on a rundown",
    "examples": []
  },
  {
    "definition": "disparage",
    "examples": []
  },
  {
    "definition": "to cease to operate because of the exhaustion of motive power",
    "examples": [
      "the clock ran down"
    ]
  },
  {
    "definition": "to decline in physical condition or vigor",
    "examples": []
  }
]