[
  {
    "definition": "to apply a short circuit to or establish a short circuit in",
    "examples": []
  },
  {
    "definition": "bypass sense 2",
    "examples": []
  },
  {
    "definition": "frustrate, impede",
    "examples": []
  },
  {
    "definition": "to become shunted by a short circuit",
    "examples": [
      "The radio short-circuited."
    ]
  },
  {
    "definition": "a connection of comparatively low resistance accidentally or intentionally made between points on a circuit between which the resistance is normally much greater",
    "examples": []
  }
]