[
  {
    "definition": "a building or structure typically higher than its diameter and high relative to its surroundings that may stand apart (such as a campanile) or be attached (such as a church belfry) to a larger structure and that may be fully walled in or of skeleton framework (such as an observation or transmission tower)",
    "examples": []
  },
  {
    "definition": "a towering citadel : fortress",
    "examples": []
  },
  {
    "definition": "one that provides support or protection : bulwark",
    "examples": [
      "a tower of strength"
    ]
  },
  {
    "definition": "a personal computer case that stands in an upright position",
    "examples": []
  },
  {
    "definition": "to reach or rise to a great height",
    "examples": []
  },
  {
    "definition": "to exhibit superior qualities : surpass",
    "examples": [
      "her intellect towered over the others\u0027"
    ]
  }
]