[
  {
    "definition": "assured reliance on the character, ability, strength, or truth of someone or something",
    "examples": []
  },
  {
    "definition": "one in which confidence is placed",
    "examples": []
  },
  {
    "definition": "dependence on something future or contingent : hope",
    "examples": []
  },
  {
    "definition": "reliance on future payment for property (such as merchandise) delivered : credit",
    "examples": [
      "bought furniture on trust"
    ]
  },
  {
    "definition": "a property interest held by one person for the benefit of another",
    "examples": []
  },
  {
    "definition": "a combination of firms or corporations formed by a legal agreement, one that reduces or threatens to reduce competition",
    "examples": []
  },
  {
    "definition": "care, custody",
    "examples": [
      "the child committed to her trust"
    ]
  },
  {
    "definition": "a charge or duty imposed in faith or confidence or as a condition of some relationship, something committed or entrusted to one to be used or cared for in the interest of another",
    "examples": []
  },
  {
    "definition": "responsible charge or office",
    "examples": []
  },
  {
    "definition": "trustworthiness",
    "examples": []
  },
  {
    "definition": "in the care or possession of a trustee",
    "examples": []
  },
  {
    "definition": "to rely on the truthfulness or accuracy of : believe",
    "examples": [
      "trust a rumor"
    ]
  },
  {
    "definition": "to place confidence in : rely on",
    "examples": [
      "a friend you can trust"
    ]
  },
  {
    "definition": "to hope or expect confidently",
    "examples": [
      "trusts that the problem will be resolved soon"
    ]
  },
  {
    "definition": "to commit or place in one\u0027s care or keeping : entrust",
    "examples": []
  },
  {
    "definition": "to permit to stay or go or to do something without fear or misgiving",
    "examples": []
  },
  {
    "definition": "to extend credit to",
    "examples": []
  },
  {
    "definition": "to place confidence : depend",
    "examples": [
      "trust in God",
      "trust to luck"
    ]
  },
  {
    "definition": "to be confident : hope",
    "examples": []
  },
  {
    "definition": "to sell or deliver on credit",
    "examples": []
  }
]