[
  {
    "definition": "one who has no established residence and wanders idly from place to place without lawful or visible means of support",
    "examples": []
  },
  {
    "definition": "one (such as a prostitute or drunkard) whose conduct constitutes statutory vagrancy",
    "examples": []
  },
  {
    "definition": "wanderer, rover",
    "examples": []
  },
  {
    "definition": "an animal wandering outside its normal geographic range, a bird found outside its normal geographic range or migration route : accidental",
    "examples": [
      "California gulls have turned up as vagrants in other nearby states, including New York, Maryland and Pennsylvania.",
      "— Pete Bacinski and Scott Barnes"
    ]
  },
  {
    "definition": "wandering about from place to place usually with no means of support",
    "examples": []
  },
  {
    "definition": "wandering outside its normal geographic range, found outside its normal geographic range or migration route : accidental sense 3",
    "examples": []
  },
  {
    "definition": "having a fleeting, wayward, or inconstant quality",
    "examples": [
      "a vagrant impulse"
    ]
  },
  {
    "definition": "having no fixed course : random",
    "examples": [
      "a vagrant breeze"
    ]
  }
]