[
  {
    "definition": "blood vessel, any of the tubular branching vessels that carry blood from the capillaries toward the heart",
    "examples": []
  },
  {
    "definition": "any of the vascular bundles forming the framework of a leaf",
    "examples": []
  },
  {
    "definition": "any of the thickened cuticular ribs that serve to stiffen the wings of an insect",
    "examples": []
  },
  {
    "definition": "a narrow water channel in rock or earth or in ice",
    "examples": []
  },
  {
    "definition": "lode sense 2, a bed of useful mineral matter",
    "examples": []
  },
  {
    "definition": "lode sense 3",
    "examples": []
  },
  {
    "definition": "something suggesting veins (as in reticulation), a wavy variegation (as in marble)",
    "examples": []
  },
  {
    "definition": "a distinctive mode of expression : style",
    "examples": [
      "stories in a romantic vein"
    ]
  },
  {
    "definition": "a distinctive element or quality : strain",
    "examples": [
      "introduced a welcome vein of humor"
    ]
  },
  {
    "definition": "a line of thought or action",
    "examples": []
  },
  {
    "definition": "a special aptitude",
    "examples": [
      "inherited an artistic vein"
    ]
  },
  {
    "definition": "a usually transitory and casually attained mood",
    "examples": []
  },
  {
    "definition": "top form",
    "examples": [
      "thou troublest me; I am not in the vein",
      "— William Shakespeare"
    ]
  },
  {
    "definition": "to pattern with or as if with veins",
    "examples": []
  }
]